 [
   {
            "rpc": "https://arb1.arbitrum.io/rpc",
            "chartTool": "https://www.dextools.io/app/en/arbitrum/pair-explorer/",
            "chainId": 42161,
            "explorer": "https://arbiscan.io",
            "accountName": "ethereum",
            "historyId": "arbitrum-mainnet"
        }, 
   {
    "asset": "c10009000_t0x23cD2E6b283754Fd2340a75732f9DdBb5d11807e",    
            "type": "ARBITRUM",
            "address": "0x912CE59144191C1204E64559FE8253a0e49E6548",
            "name": "Arbitrum",
            "symbol": "ARB",
          "cmcId": "https://coinmarketcap.com/currencies/arbitrum/",
    "description": "$ARB tokens can be used to vote on Arbitrum DAO governance proposals, allowing $ARB holders to collectively shape the future of Arbitrum protocols and chains. Token holders can also delegate their voting power to delegates.",
            "decimals": 18,
            "logoURI": "https://s2.coinmarketcap.com/static/img/coins/64x64/11841.png",
            "pairs": []
        },
        {
           "asset": "c10009000_t0x23cD2E6b283754Fd2340a75732f9DdBb5d11807e",
            "type": "ARBITRUM",
            "address": "0x82aF49447D8a07e3bd95BD0d56f35241523fBab1",
            "name": "Wrapped Ether",
            "symbol": "WETH",
          "cmcId": "https://coinmarketcap.com/currencies/ethereum/",
            "decimals": 18,
            "logoURI": "https://assets-cdn.trustwallet.com/blockchains/arbitrum/assets/0x82aF49447D8a07e3bd95BD0d56f35241523fBab1/logo.png",
            "pairs": []
        },
        {
           "asset": "c10009000_t0x23cD2E6b283754Fd2340a75732f9DdBb5d11807e",
            "type": "ARBITRUM",
            "address": "0xFF970A61A04b1cA14834A43f5dE4533eBDDB5CC8",
            "name": "Bridged USDC",
            "symbol": "USDC.e",
            "decimals": 6,
          "cmcId": "https://coinmarketcap.com/currencies/usd-coin/",
            "logoURI": "https://assets-cdn.trustwallet.com/blockchains/arbitrum/assets/0xFF970A61A04b1cA14834A43f5dE4533eBDDB5CC8/logo.png",
            "pairs": []
        },
        {
          "asset": "c10009000_t0x23cD2E6b283754Fd2340a75732f9DdBb5d11807e",
            "type": "ARBITRUM",
            "address": "0xDA10009cBd5D07dd0CeCc66161FC93D7c9000da1",
            "name": "Dai Stablecoin",
            "symbol": "DAI",
          "cmcId": "https://coinmarketcap.com/currencies/multi-collateral-dai/",
            "decimals": 18,
            "logoURI": "https://assets-cdn.trustwallet.com/blockchains/arbitrum/assets/0xDA10009cBd5D07dd0CeCc66161FC93D7c9000da1/logo.png",
            "pairs": []
        },
        {
           "asset": "c10009000_t0x23cD2E6b283754Fd2340a75732f9DdBb5d11807e",
            "type": "ARBITRUM",
            "address": "0xFd086bC7CD5C481DCC9C85ebE478A1C0b69FCbb9",
            "name": "Tether USD",
            "symbol": "USDT",
            "decimals": 6,
          "cmcId": "https://coinmarketcap.com/currencies/tether/",
            "logoURI": "https://assets-cdn.trustwallet.com/blockchains/arbitrum/assets/0xFd086bC7CD5C481DCC9C85ebE478A1C0b69FCbb9/logo.png",
            "pairs": []
        },
        {
            "asset": "c10009000_t0x23cD2E6b283754Fd2340a75732f9DdBb5d11807e",
            "type": "ARBITRUM",
            "address": "0xfc5A1A6EB076a2C7aD06eD22C90d7E710E35ad0a",
            "name": "GMX",
            "symbol": "GMX",
          "cmcId": "https://coinmarketcap.com/currencies/gmx/",
            "decimals": 18,
            "logoURI": "https://assets-cdn.trustwallet.com/blockchains/arbitrum/assets/0xfc5A1A6EB076a2C7aD06eD22C90d7E710E35ad0a/logo.png",
            "pairs": []
        },
        {
        "asset": "c10009000_t0x23cD2E6b283754Fd2340a75732f9DdBb5d11807e",
            "type": "ARBITRUM",
            "address": "0x9623063377AD1B27544C965cCd7342f7EA7e88C7",
            "name": "The Graph",
            "symbol": "GRT",
          "cmcId": "https://coinmarketcap.com/currencies/the-graph/",
            "decimals": 18,
            "logoURI": "https://assets-cdn.trustwallet.com/blockchains/arbitrum/assets/0x9623063377AD1B27544C965cCd7342f7EA7e88C7/logo.png",
            "pairs": []
        }
    ]
